pydmtxlib/__init__.py
pydmtxlib/dmtx_library.py
pydmtxlib/pydmtxlib.py
pydmtxlib/pydmtxlib_error.py
pydmtxlib/wrapper.py
pydmtxlib/scripts/__init__.py
pydmtxlib/scripts/read_datamatrix.py
pydmtxlib/scripts/write_datamatrix.py
pydmtxlib/tests/__init__.py
pydmtxlib/tests/datamatrix.png
pydmtxlib/tests/empty.png
pydmtxlib/tests/test_dmtx_library.py
pydmtxlib/tests/test_pydmtxlib.py
pydmtxlib/tests/test_read_write_datamatrix.py
pydmtxlib-0.2.3.data/scripts/read_datamatrix.py
pydmtxlib-0.2.3.data/scripts/write_datamatrix.py
pydmtxlib-0.2.3.dist-info/licenses/LICENSE.txt
pydmtxlib-0.2.3.dist-info/METADATA
pydmtxlib-0.2.3.dist-info/WHEEL
pydmtxlib-0.2.3.dist-info/entry_points.txt
pydmtxlib-0.2.3.dist-info/top_level.txt
pydmtxlib-0.2.3.dist-info/RECORD
