Metadata-Version: 2.4
Name: pydmtxlib
Version: 0.2.3
Summary: Read and write Data Matrix from Python 3.8 and above.
Home-page: https://github.com/pylibhub/pydmtxlib
Author: pylibhub
Author-email: pylibhub@gmail.com
License: MIT
Classifier: Development Status :: 4 - Beta
Classifier: License :: OSI Approved :: MIT License
Classifier: Topic :: Utilities
Classifier: Programming Language :: Python :: 3.8
Classifier: Programming Language :: Python :: 3.9
Classifier: Programming Language :: Python :: 3.10
Classifier: Programming Language :: Python :: 3.11
Classifier: Programming Language :: Python :: 3.12
Classifier: Programming Language :: Python :: 3.13
License-File: LICENSE.txt
Requires-Dist: packaging>=25.0
Provides-Extra: scripts
Requires-Dist: Pillow>=3.2.0; extra == "scripts"
Dynamic: author
Dynamic: author-email
Dynamic: classifier
Dynamic: description
Dynamic: description-content-type
Dynamic: home-page
Dynamic: license
Dynamic: license-file
Dynamic: provides-extra
Dynamic: requires-dist
Dynamic: summary
